commands/__init__.py
commands/cat/Dr-Egeria_md-orig.py
commands/cat/__init__.py
commands/cat/collection_actions.py
commands/cat/dr_egeria_command_help.py
commands/cat/dr_egeria_jupyter.py
commands/cat/dr_egeria_md.py
commands/cat/exp_list_glossaries.py
commands/cat/get_asset_graph.py
commands/cat/get_collection_tree.py
commands/cat/get_project_dependencies.py
commands/cat/get_project_structure.py
commands/cat/get_tech_type_elements.py
commands/cat/glossary_actions.py
commands/cat/list_assets.py
commands/cat/list_cert_types.py
commands/cat/list_collections.py
commands/cat/list_deployed_catalogs.py
commands/cat/list_deployed_database_schemas.py
commands/cat/list_deployed_databases.py
commands/cat/list_deployed_servers.py
commands/cat/list_glossaries.py
commands/cat/list_projects.py
commands/cat/list_tech_type_elements.py
commands/cat/list_tech_types.py
commands/cat/list_terms.py
commands/cat/list_todos.py
commands/cat/list_user_ids.py
commands/cat/my_reports.py
commands/cat/run_report.py
commands/cat/run_report_orig.py
commands/cli/__init__.py
commands/cli/egeria.py
commands/cli/egeria_cat.py
commands/cli/egeria_login_tui.py
commands/cli/egeria_my.py
commands/cli/egeria_ops.py
commands/cli/egeria_tech.py
commands/cli/ops_config.py
commands/deprecated/list_data_designer.py
commands/deprecated/list_data_structures_full.py
commands/deprecated/old_get_asset_graph.py
commands/my/__init__.py
commands/my/list_my_profile.py
commands/my/list_my_roles.py
commands/my/monitor_my_todos.py
commands/my/monitor_open_todos.py
commands/my/todo_actions.py
commands/ops/__init__.py
commands/ops/gov_server_actions.py
commands/ops/list_archives.py
commands/ops/list_catalog_targets.py
commands/ops/load_archive.py
commands/ops/monitor_active_engine_activity.py
commands/ops/monitor_daemon_status.py
commands/ops/monitor_engine_activity.py
commands/ops/monitor_engine_status.py
commands/ops/monitor_platform_status.py
commands/ops/monitor_server_startup.py
commands/ops/monitor_server_status.py
pyegeria-5.5.2.dist-info/licenses/LICENSE
pyegeria-5.5.2.dist-info/METADATA
pyegeria-5.5.2.dist-info/WHEEL
pyegeria-5.5.2.dist-info/entry_points.txt
pyegeria-5.5.2.dist-info/top_level.txt
pyegeria-5.5.2.dist-info/RECORD
