Metadata-Version: 2.4
Name: pyegeria
Version: 5.5.2
Summary: A python client for Egeria
Author-email: Dan Wolfson <dan.wolfson@pdr-associates.com>
License-Expression: Apache-2.0
Keywords: egeria,metadata,governance
Classifier: Programming Language :: Python
Classifier: Programming Language :: Python :: 3
Requires-Python: >3.12
License-File: LICENSE
Requires-Dist: httpx
Requires-Dist: rich>=14.2
Requires-Dist: validators
Requires-Dist: urllib3
Requires-Dist: requests
Requires-Dist: jupyter
Requires-Dist: click==8.3.1
Requires-Dist: trogon
Requires-Dist: psycopg2-binary>=2.9.11
Requires-Dist: jupyter-notebook-parser
Requires-Dist: loguru
Requires-Dist: inflect
Requires-Dist: pydantic>=2.12.3
Requires-Dist: pydantic-settings>=2.10.1
Requires-Dist: pydevd-pycharm>=253.27642.35
Requires-Dist: wcwidth
Requires-Dist: altair==6.0.0
Requires-Dist: mcp>=0.1
Requires-Dist: markers>=0.3.0
Requires-Dist: pytest-asyncio>=1.2.0
Requires-Dist: python-dotenv>=1.1.1
Provides-Extra: test
Requires-Dist: pytest; extra == "test"
Dynamic: license-file
